{
  "project_info": {
    "project_number": "184189433871",
    "firebase_url": "https://explorer-ab6f0.firebaseio.com",
    "project_id": "explorer-ab6f0",
    "storage_bucket": "explorer-ab6f0.appspot.com"
  },
  "client": [
    {
      "client_info": {
        "mobilesdk_app_id": "1:184189433871:android:61ff8b9a2c343bd8558b7a",
        "android_client_info": {
          "package_name": "com.example.explorer"
        }
      },
      "oauth_client": [
        {
          "client_id": "184189433871-bo2197esrq9rqa9ubbacko2r17l78scv.apps.googleusercontent.com",
          "client_type": 3
        }
      ],
      "api_key": [
        {
          "current_key": "AIzaSyCCbSDMdlqaFGSAgS4kFb2XTNezeC4vC_I"
        }
      ],
      "services": {
        "appinvite_service": {
          "other_platform_oauth_client": [
            {
              "client_id": "184189433871-bo2197esrq9rqa9ubbacko2r17l78scv.apps.googleusercontent.com",
              "client_type": 3
            }
          ]
        }
      }
    }
  ],
  "configuration_version": "1"
}